mcp_server_foxit_cloudapi/__init__.py
mcp_server_foxit_cloudapi/__main__.py
mcp_server_foxit_cloudapi/action/apply_certificate.py
mcp_server_foxit_cloudapi/action/combine_pdf.py
mcp_server_foxit_cloudapi/action/compare_pdf.py
mcp_server_foxit_cloudapi/action/compress_pdf.py
mcp_server_foxit_cloudapi/action/convert_pdf.py
mcp_server_foxit_cloudapi/action/create_pdf.py
mcp_server_foxit_cloudapi/action/create_pdf_from_html.py
mcp_server_foxit_cloudapi/action/extract_pdf.py
mcp_server_foxit_cloudapi/action/flatten_pdf.py
mcp_server_foxit_cloudapi/action/linearize_pdf.py
mcp_server_foxit_cloudapi/action/manipulation_pdf.py
mcp_server_foxit_cloudapi/action/pages_basic_info.py
mcp_server_foxit_cloudapi/action/pages_is_scanned.py
mcp_server_foxit_cloudapi/action/protect_pdf.py
mcp_server_foxit_cloudapi/action/remove_password.py
mcp_server_foxit_cloudapi/action/sign_pdf.py
mcp_server_foxit_cloudapi/action/split_pdf.py
mcp_server_foxit_cloudapi/action/watermark_pdf.py
mcp_server_foxit_cloudapi/common/constant.py
mcp_server_foxit_cloudapi/common/service.py
mcp_server_foxit_cloudapi/common/util.py
mcp_server_foxit_cloudapi/server.py
mcp_server_foxit_cloudapi-1.1.1.dist-info/WHEEL
mcp_server_foxit_cloudapi-1.1.1.dist-info/entry_points.txt
mcp_server_foxit_cloudapi-1.1.1.dist-info/METADATA
mcp_server_foxit_cloudapi-1.1.1.dist-info/RECORD
