Metadata-Version: 2.3
Name: mcp-server-foxit-cloudapi
Version: 1.1.1
Summary: MCP server for using the Foxit Cloud API
Keywords: MCP,Foxit,Cloud API
Author: Foxit Software Inc.
Author-email: Foxit Software Inc. <support@foxitsoftware.com>
License: Commercial License
Requires-Dist: httpx==0.28.1
Requires-Dist: jsonschema==4.23.0
Requires-Dist: mcp==1.13.1
Requires-Python: >=3.11.1
